scheme8/__init__.py
scheme8/__main__.py
scheme8-0.1.dev0.dist-info/LICENSE
scheme8-0.1.dev0.dist-info/METADATA
scheme8-0.1.dev0.dist-info/WHEEL
scheme8-0.1.dev0.dist-info/entry_points.txt
scheme8-0.1.dev0.dist-info/top_level.txt
scheme8-0.1.dev0.dist-info/RECORD
