Metadata-Version: 2.1
Name: scheme8
Version: 0.1.dev0
Summary: scheme8
Home-page: https://github.com/pycontribs/scheme8
Author: Sorin Sbarnea
Author-email: sorin.sbarnea@gmail.com
License: MIT
Project-URL: Source, https://github.com/pycontribs/scheme8
Project-URL: Tracker, https://github.com/tox-dev/pycontribs/scheme8
Platform: UNKNOWN
Classifier: License :: OSI Approved :: MIT License
Classifier: Programming Language :: Python :: 2
Classifier: Programming Language :: Python :: 2.7
Classifier: Programming Language :: Python :: 3
Classifier: Programming Language :: Python :: 3.5
Classifier: Programming Language :: Python :: 3.6
Classifier: Programming Language :: Python :: 3.7
Classifier: Programming Language :: Python :: 3.8
Classifier: Programming Language :: Python :: Implementation :: CPython
Classifier: Programming Language :: Python :: Implementation :: PyPy
Requires-Python: !=3.0.*,!=3.1.*,!=3.2.*,!=3.3.*,!=3.4.*,>=2.7
Requires-Dist: pyyaml
Requires-Dist: jsonschema
Requires-Dist: six
Requires-Dist: typing ; python_version < "3.5"
